{"_type":"export","__export_format":4,"__export_date":"2023-02-26T01:18:31.325Z","__export_source":"insomnia.desktop.app:v2022.7.5","resources":[{"_id":"req_860af0531ed34c359090a435d9988ae2","parentId":"fld_127cab6015674951b721841fa9dd2522","modified":1677374241628,"created":1677078188106,"url":"{{ _.local_host }}devices","name":"CREATE [ Device ] Sem informações","description":"","method":"POST","body":{"mimeType":"application/json","text":"{\n\t\"title\": \"Impressora\",\n\t\"description\": \"Impressora multifuncional a laser.\"\n}"},"parameters":[],"headers":[{"name":"Content-Type","value":"application/json"}],"authentication":{},"metaSortKey":-1677084413169,"isPrivate":false,"settingStoreCookies":true,"settingSendCookies":true,"settingDisableRenderRequestBody":false,"settingEncodeUrl":true,"settingRebuildPath":true,"settingFollowRedirects":"global","_type":"request"},{"_id":"fld_127cab6015674951b721841fa9dd2522","parentId":"wrk_0376488ccc6b4656bc40cdeeab8ca7aa","modified":1677090638232,"created":1677090638232,"name":"Devices","description":"","environment":{},"environmentPropertyOrder":null,"metaSortKey":-1677090638232,"_type":"request_group"},{"_id":"wrk_0376488ccc6b4656bc40cdeeab8ca7aa","parentId":null,"modified":1677078177022,"created":1677078177022,"name":"Devices IoT","description":"","scope":"collection","_type":"workspace"},{"_id":"req_bac462de8be744729b721481974767fb","parentId":"fld_127cab6015674951b721841fa9dd2522","modified":1677374140876,"created":1677163704846,"url":"{{ _.local_host }}devices","name":"CREATE [ Device ] Duas infomaçãos, uma com valor de unidade","description":"","method":"POST","body":{"mimeType":"application/json","text":"{\n\t\"title\": \"Câmera de segurança\",\n\t\"description\": \"Vigilância Eletrônica por Vídeo.\",\n\t\"info\":[\n\t\t\t{\n\t\t\t\t\t\"name\": \"Qualidade da imagem\",\n\t\t\t\t\t\"value\": 11,\n\t\t\t\t\t\"unity\": \"PPI\"\n\t\t\t},\n\t\t\t{\n\t\t\t\t\t\"name\": \"Sensor de luminosidade\",\n\t\t\t\t\t\"unity\": \"lx\"\n\t\t\t}\n\t]\t\n}"},"parameters":[],"headers":[{"name":"Content-Type","value":"application/json"}],"authentication":{},"metaSortKey":-1677084413144,"isPrivate":false,"settingStoreCookies":true,"settingSendCookies":true,"settingDisableRenderRequestBody":false,"settingEncodeUrl":true,"settingRebuildPath":true,"settingFollowRedirects":"global","_type":"request"},{"_id":"req_af354ab2918341a1b57fc44b6eb3f802","parentId":"fld_127cab6015674951b721841fa9dd2522","modified":1677374208052,"created":1677164219007,"url":"{{ _.local_host }}devices","name":"CREATE [ Device ] Duas informações sem valor de unidade","description":"","method":"POST","body":{"mimeType":"application/json","text":"{\n\t\"title\": \"Sensor de umidade e temperatura\",\n\t\"description\": \"Dispositivo eletrônico utilizado para medir e monitorar a temperatura e umidade do ar em diversos ambientes.\",\n\t\"info\":[\n\t\t{\n\t\t\t\"name\": \"humidade\",\n\t\t\t\"unity\": \"%\"\n\t\t},\n\t\t{\n\t\t\t\"name\": \"temperatura\",\n\t\t\t\"unity\": \"°F\"\n\t\t}\n\t]\t\n}"},"parameters":[],"headers":[{"name":"Content-Type","value":"application/json"}],"authentication":{},"metaSortKey":-1677084413131.5,"isPrivate":false,"settingStoreCookies":true,"settingSendCookies":true,"settingDisableRenderRequestBody":false,"settingEncodeUrl":true,"settingRebuildPath":true,"settingFollowRedirects":"global","_type":"request"},{"_id":"req_9343e5eef7584fc3b5068124f345a52f","parentId":"fld_127cab6015674951b721841fa9dd2522","modified":1677091557655,"created":1677078625995,"url":"{{ _.local_host }}devices","name":"LIST ALL [ Devices ]","description":"","method":"GET","body":{},"parameters":[],"headers":[],"authentication":{},"metaSortKey":-1677084413119,"isPrivate":false,"settingStoreCookies":true,"settingSendCookies":true,"settingDisableRenderRequestBody":false,"settingEncodeUrl":true,"settingRebuildPath":true,"settingFollowRedirects":"global","_type":"request"},{"_id":"req_6f6f915d9c774739985208920ec8d528","parentId":"fld_127cab6015674951b721841fa9dd2522","modified":1677370630129,"created":1677091552243,"url":"{{ _.local_host }}devices/63fa36de9e230c9b6dc0f7a9","name":"LIST ONE [ Device ]","description":"","method":"GET","body":{},"parameters":[],"headers":[],"authentication":{},"metaSortKey":-1677084413094,"isPrivate":false,"settingStoreCookies":true,"settingSendCookies":true,"settingDisableRenderRequestBody":false,"settingEncodeUrl":true,"settingRebuildPath":true,"settingFollowRedirects":"global","_type":"request"},{"_id":"req_941e2df49c1f4accbf14a679942d53b7","parentId":"fld_127cab6015674951b721841fa9dd2522","modified":1677370689312,"created":1677090611633,"url":"{{ _.local_host }}devices/63fa36de9e230c9b6dc0f7a9","name":"OPDATE [ Device ]","description":"","method":"PATCH","body":{"mimeType":"application/json","text":"{\n\t\t\"description\": \"Vigilância\"\n}"},"parameters":[],"headers":[{"name":"Content-Type","value":"application/json"}],"authentication":{},"metaSortKey":-1677084413069,"isPrivate":false,"settingStoreCookies":true,"settingSendCookies":true,"settingDisableRenderRequestBody":false,"settingEncodeUrl":true,"settingRebuildPath":true,"settingFollowRedirects":"global","_type":"request"},{"_id":"req_1ebaedfe382f40ca97404660ae0c760c","parentId":"fld_127cab6015674951b721841fa9dd2522","modified":1677343886733,"created":1677090625326,"url":"{{ _.local_host }}devices/63f90f3966069bc160895c91","name":"DELETE [ Device ]","description":"","method":"DELETE","body":{},"parameters":[],"headers":[],"authentication":{},"metaSortKey":-1677084413019,"isPrivate":false,"settingStoreCookies":true,"settingSendCookies":true,"settingDisableRenderRequestBody":false,"settingEncodeUrl":true,"settingRebuildPath":true,"settingFollowRedirects":"global","_type":"request"},{"_id":"env_0d2be3cc0177e2b43aa3710fed341bf6942790ea","parentId":"wrk_0376488ccc6b4656bc40cdeeab8ca7aa","modified":1677078477158,"created":1677078177028,"name":"Base Environment","data":{"local_host":"http://localhost:3333/"},"dataPropertyOrder":{"&":["local_host"]},"color":null,"isPrivate":false,"metaSortKey":1677078177028,"_type":"environment"},{"_id":"jar_0d2be3cc0177e2b43aa3710fed341bf6942790ea","parentId":"wrk_0376488ccc6b4656bc40cdeeab8ca7aa","modified":1677078177030,"created":1677078177030,"name":"Default Jar","cookies":[],"_type":"cookie_jar"},{"_id":"spc_8b3a05fa1dea4807a2bf6889f9c75ac7","parentId":"wrk_0376488ccc6b4656bc40cdeeab8ca7aa","modified":1677078177023,"created":1677078177023,"fileName":"Devices IoT","contents":"","contentType":"yaml","_type":"api_spec"}]}